{
  "Unit Tests": {
    "coverage": {
      "/Users/Home/Turing/1module/battleship/lib/board.rb": [
        1,
        1,
        1,
        1,
        null,
        1,
        11,
        11,
        null,
        null,
        1,
        14,
        99,
        null,
        null,
        null,
        1,
        8,
        null,
        null,
        1,
        2,
        2,
        null,
        null,
        1,
        2,
        2,
        null,
        null,
        1,
        10,
        5,
        null,
        5,
        null,
        10,
        null,
        null,
        1,
        2,
        1,
        null,
        1,
        null,
        null,
        null,
        1,
        null,
        1,
        10,
        25,
        25,
        null,
        10,
        null,
        null,
        1,
        29,
        29,
        null,
        null,
        1,
        29,
        null,
        29,
        29,
        29,
        null,
        null,
        1,
        5,
        4,
        null,
        1,
        null,
        5,
        null,
        null,
        1,
        4,
        null,
        null,
        1,
        1,
        null,
        null,
        1,
        5,
        null,
        null,
        null,
        null,
        null,
        null
      ],
      "/Users/Home/Turing/1module/battleship/lib/boards.rb": [
        1,
        1,
        null,
        null,
        null,
        null,
        null,
        1,
        null,
        null,
        null,
        null,
        null,
        1,
        72,
        8,
        8,
        8,
        8,
        null,
        null,
        1,
        56,
        56,
        null,
        null,
        1,
        8,
        48,
        8,
        null,
        40,
        null,
        null,
        null,
        null,
        1,
        8,
        64,
        24,
        null,
        40,
        null,
        null,
        null,
        null
      ]
    },
    "timestamp": 1491160932
  },
  "MiniTest": {
    "coverage": {
    },
    "timestamp": 1491161508
  }
}
